apiseek/__init__.py
apiseek/core.py
apiseek/static/style.css
apiseek/templates/apiseek.html
apiseek/templates/base.html
apiseek/templates/dataseek.html
apiseek/templates/visualseek.html
apiseek-0.3.dist-info/LICENSE
apiseek-0.3.dist-info/METADATA
apiseek-0.3.dist-info/WHEEL
apiseek-0.3.dist-info/top_level.txt
apiseek-0.3.dist-info/RECORD
